remixqq_python_sdk/__init__.py
remixqq_python_sdk/app.py
RemixQQ_Python_SDK-20240430171818.dist-info/LICENSE
RemixQQ_Python_SDK-20240430171818.dist-info/METADATA
RemixQQ_Python_SDK-20240430171818.dist-info/WHEEL
RemixQQ_Python_SDK-20240430171818.dist-info/top_level.txt
RemixQQ_Python_SDK-20240430171818.dist-info/RECORD
