Metadata-Version: 2.1
Name: RemixQQ_Python_SDK
Version: 20240430171818
Summary: A python SDK for RemixQQ connected by httpapi
Author-email: 404_NOT_FOUND <1127738407@qq.com>
License: MIT
Project-URL: Homepage, https://github.com/willyautoman/RemixQQ_Python_SDK
Project-URL: Bug Tracker, https://github.com/willyautoman/RemixQQ_Python_SDK/issues
Requires-Python: >=3.8
License-File: LICENSE
Requires-Dist: requests >=2.31.0
